{
    "5th ICSE": [
        "Laaibah",
        "Ghulam",
        "Azhan"
    ],
    "6th ICSE": [
        "Azlaan",
        "Juwariya",
        "Usman",
        "Afraan",
        "Arsh",
        "Saad",
        "Nurain",
        "Muhammad",
        "Zeeshan",
        "Adyan",
        "Nizamuddin",
        "Wahid",
        "Asad",
        "Zohed"
    ],
    "7th ICSE": [
        "Mehveen",
        "Anam",
        "Ammar",
        "Arsh",
        "Muznah",
        "Zahra",
        "Yasin",
        "Muad",
        "Mustafa",
        "Arsalan",
        "S Ayaan",
        "Zaid",
        "K Ayaan",
        "B Ayaan",
        "Naverah",
        "Ahtesham",
        "Kabir"
    ],
    "8th ICSE": [
        "Zarah",
        "Fahad",
        "Shamica",
        "Waliyah",
        "Lishika",
        "M Ayesha",
        "Zaina",
        "Gufrana",
        "Arshiya",
        "Juveriya",
        "S Ayesha",
        "Owais",
        "Gaus Khan",
        "Razeen",
        "Kaif",
        "Gulam Ghaus",
        "Arhan",
        "Faiz",
        "Ahad",
        "Faraz",
        "Ayan Faiz",
        "Ayan Ali",
        "Rayan",
        "Fazlurrehman",
        "Shafaat",
        "Rayed",
        "Alishba",
        "Akif",
        "Talha",
        "Raiyan",
        "Abid",
        "Moinuddin",
        "Harikesh"
    ],
    "9th ICSE": [
        "Zohra",
        "Beenish",
        "Haashir",
        "Saara",
        "Saad Rumani",
        "Amaan",
        "Umar",
        "Hamza",
        "Ashar",
        "Affan",
        "Armaan",
        "Ahad",
        "Maria",
        "Maseera",
        "Juveriya",
        "Naba",
        "Zainab",
        "Ridaan",
        "K Mehvish",
        "Saad Khan"
    ],
    "10th ICSE": [
        "Nada",
        "Falak",
        "Tabassum",
        "Aroot",
        "Rida",
        "Aleeza",
        "Eeman",
        "Eram",
        "Asad",
        "Ahnaf",
        "Aquib",
        "Raza",
        "Faizan",
        "Ammar",
        "Arsalan P",
        "Arsalan M",
        "Affan",
        "Ayaz",
        "Eisa",
        "Ayaan S",
        "Arhaan",
        "Noor",
        "Arqam",
        "Ali",
        "Hasnain"
    ],
    "9th Symbiosis": [
        "Aayat",
        "Saad",
        "Abdullah",
        "Walid",
        "Rehan",
        "Arzeesh"
    ],
    "9th General": [
        "Shahbaaz",
        "Priyanshu",
        "Masihuddin",
        "Rabiya",
        "Mursalim",
        "Yusuf",
        "Ashrafiya",
        "Muzammil",
        "Aliya"
    ],
    "10th SSC": [
        "Adib",
        "Yaseen",
        "Mustufa",
        "Zunairah",
        "Amaan",
        "Humaira",
        "Hammad",
        "Fahima",
        "Umme Ayman",
        "Zaid",
        "Saim",
        "Sameer"
    ]
}
